<?xml version="1.0" encoding="utf-8" ?>
<Recipe xmlns:xsi="http://www.w3.org/2001/XMLSchema-instance"
xmlns:xsd="http://www.w3.org/2001/XMLSchema"
Name="CustomActionProgId"
xmlns="http://schemas.microsoft.com/pag/gax-core"
Bound="false">
  <xi:include href="../../../TypeAlias.xml" xmlns:xi="http://www.w3.org/2001/XInclude" />
  <Caption>Custom Action for ProgID (Document Type)</Caption>
  <Description>Adds a custom action to a document type e.g. "InfoPath.Document"</Description>
  <HostData Priority="30">
    <Icon File="Help/Icons/icon_CustomActions.ico" />
    <CommandBar Menu="SPSFProjectCustomActions"/>
    <CommandBar Menu="SPSFFolderCustomActions"/>
    <spsf:MetaData
      Visible="true"
      BindingType="ElementManifestReference"
      BindingTypeTemplate="ElementManifestReferenceTemplate"
      TestType="BaseSiteFeatureRecipeRunner"
      Enabled="true"
      CreateVSTemplate="true"
      FeatureScopes="Web;Site;WebApplication;Farm"
      Category="CustomActions" xmlns:spsf="http://spsf.codeplex.com">
      <spsf:Authors>
        <spsf:Author>Torsten Mandelkow</spsf:Author>
      </spsf:Authors>
      <spsf:VersionHistory>
        <spsf:VersionHistoryEntry>1.0 Initial Recipe</spsf:VersionHistoryEntry>
      </spsf:VersionHistory>
      <spsf:WebPageContent>
        <![CDATA[]]>
      </spsf:WebPageContent>
      <spsf:Test>
        <spsf:TestCases>
          <spsf:TestCase Name="CustomActionProgIdWithUrlAction" Type="SolutionTestCase">
            <spsf:TestCaseArguments>
              <spsf:TestCaseArgument Name="CustomActionName">ProgIdActionUrlAction</spsf:TestCaseArgument>
              <spsf:TestCaseArgument Name="CustomActionType">UrlActionTag</spsf:TestCaseArgument>
            </spsf:TestCaseArguments>
          </spsf:TestCase>
          <spsf:TestCase Name="CustomActionProgIdWithControlClass" Type="SolutionTestCase">
            <spsf:TestCaseArguments>
              <spsf:TestCaseArgument Name="CustomActionName">ProgIdActionControlClass</spsf:TestCaseArgument>
              <spsf:TestCaseArgument Name="CustomActionType">ClassFile</spsf:TestCaseArgument>
            </spsf:TestCaseArguments>
          </spsf:TestCase>
          <spsf:TestCase Name="CustomActionProgIdWithControlTemplate">
            <spsf:TestCaseArguments>
              <spsf:TestCaseArgument Name="CustomActionName">ProgIdActionControlTemplate</spsf:TestCaseArgument>
              <spsf:TestCaseArgument Name="CustomActionType">WebControl</spsf:TestCaseArgument>
            </spsf:TestCaseArguments>
          </spsf:TestCase>
        </spsf:TestCases>
      </spsf:Test>
    </spsf:MetaData>
  </HostData>
  <Arguments>
    
    <xi:include href="../../BaseArguments.include" parse="xml" xpointer="xmlns(p=http://schemas.microsoft.com/pag/gax-core) xpointer(/p:Arguments/*)" xmlns:xi="http://www.w3.org/2001/XInclude" />
    
    <xi:include href="../BaseFeatureArguments.include" parse="xml" xpointer="xmlns(p=http://schemas.microsoft.com/pag/gax-core) xpointer(/p:Arguments/*)" xmlns:xi="http://www.w3.org/2001/XInclude" />

    <xi:include href="BaseCustomActionArguments.include" parse="xml" xpointer="xmlns(p=http://schemas.microsoft.com/pag/gax-core) xpointer(/p:Arguments/*)" xmlns:xi="http://www.w3.org/2001/XInclude" />

    <Argument Name="CustomActionRegistrationId" Type="NameValueItem" Required="true" >
      <ValueProvider Type="DefaultNameValueItemProvider" Name="docx" Value="Word.Document.12" />
    </Argument>
    <Argument Name="CustomActionRegistrationType" Required="true" >
      <ValueProvider Type="Evaluator" Expression="ProgId" />
    </Argument>
    <Argument Name="CustomActionLocation" Type="NameValueItem" Required="true" >
      <ValueProvider Type="DefaultNameValueItemProvider" Name="EditControlBlock" Value="EditControlBlock" />
    </Argument>

    <Argument Name="CustomActionAddIcon" Type="System.Boolean" Required="true">
      <ValueProvider Type="Evaluator" Expression="true" />
    </Argument>
    <Argument Name="CustomActionIconSize">
      <ValueProvider Type="Evaluator" Expression="16" />
    </Argument>

    <Argument Name="CustomActionUrlActionParameters" Type="System.String" Required="false" >
      <ValueProvider Type="Evaluator" Expression="?ItemUrl={ItemUrl}&amp;ListId={ListId}" />
    </Argument>
    <Argument Name="CustomActionElementsTemplate" Type="System.String" Required="false" >
      <ValueProvider Type="Evaluator" Expression="Text\CustomActions\elements.xml.t4" />
    </Argument>
    
  </Arguments>
  <GatheringServiceData>
    <Wizard xmlns="http://schemas.microsoft.com/pag/gax-wizards" SchemaVersion="1.0">
      <Pages>
        <Page Type="SPALM.SPSF.Library.CustomWizardPages.FeatureSelectionPage, SPALM.SPSF.Library" />
        <Page Width="600" Height="400">
          <Title>ProgId</Title>
          <Fields>
            <Field PanelType="SPALM.SPSF.Library.NameValueItemPanel, SPALM.SPSF.Library" ValueName="CustomActionRegistrationId" Label="Content Type" >
              <Help>
                Select the document type to which the custom action should be added.
              </Help>
              <Editor Type="SPALM.SPSF.Library.ProgIdEditor, SPALM.SPSF.Library" />
            </Field>
          </Fields>
        </Page>
        <!-- include general custom action pages -->
        <xi:include href="BaseCustomActionPages.include"  parse="xml" xpointer="xmlns(p=http://schemas.microsoft.com/pag/gax-wizards) xpointer(/p:Pages/*)" xmlns:xi="http://www.w3.org/2001/XInclude" />
        <xi:include href="BaseCustomActionPagesRegistration.include"  parse="xml" xpointer="xmlns(p=http://schemas.microsoft.com/pag/gax-wizards) xpointer(/p:Pages/*)" xmlns:xi="http://www.w3.org/2001/XInclude" />
        <xi:include href="BaseCustomActionPagesUrlSettings.include"  parse="xml" xpointer="xmlns(p=http://schemas.microsoft.com/pag/gax-wizards) xpointer(/p:Pages/*)" xmlns:xi="http://www.w3.org/2001/XInclude" />
      </Pages>
    </Wizard>
  </GatheringServiceData>

  <!-- include general actions -->
  <xi:include href="BaseCustomActionActions.include" xmlns:xi="http://www.w3.org/2001/XInclude" />

</Recipe>